sc3dg/__init__.py
sc3dg/cli.py
sc3dg/analysis/__init__.py
sc3dg/analysis/api.py
sc3dg/analysis/embedding.py
sc3dg/analysis/genome.py
sc3dg/bismark/Bismark_alignment_modes.pdf
sc3dg/bismark/CHANGELOG.md
sc3dg/bismark/NOMe_filtering
sc3dg/bismark/README.md
sc3dg/bismark/_config.yml
sc3dg/bismark/bam2nuc
sc3dg/bismark/bismark
sc3dg/bismark/bismark2bedGraph
sc3dg/bismark/bismark2report
sc3dg/bismark/bismark2summary
sc3dg/bismark/bismark_genome_preparation
sc3dg/bismark/bismark_methylation_extractor
sc3dg/bismark/bismark_wrapper.py
sc3dg/bismark/copy_bismark_files_for_release.pl
sc3dg/bismark/coverage2cytosine
sc3dg/bismark/deduplicate_bismark
sc3dg/bismark/filter_non_conversion
sc3dg/bismark/license.txt
sc3dg/bismark/merge_arbitrary_coverage_files.py
sc3dg/bismark/merge_coverage_files_ARGV.py
sc3dg/bismark/methylation_consistency
sc3dg/bismark/mkdocs.yml
sc3dg/bismark/test_data.fastq
sc3dg/bowtie2/AUTHORS
sc3dg/bowtie2/BOWTIE2_VERSION
sc3dg/bowtie2/LICENSE
sc3dg/bowtie2/MANUAL
sc3dg/bowtie2/MANUAL.markdown
sc3dg/bowtie2/NEWS
sc3dg/bowtie2/README.md
sc3dg/bowtie2/TUTORIAL
sc3dg/bowtie2/bowtie2
sc3dg/bowtie2/bowtie2-align-l
sc3dg/bowtie2/bowtie2-align-l-debug
sc3dg/bowtie2/bowtie2-align-s
sc3dg/bowtie2/bowtie2-align-s-debug
sc3dg/bowtie2/bowtie2-build
sc3dg/bowtie2/bowtie2-build-l
sc3dg/bowtie2/bowtie2-build-l-debug
sc3dg/bowtie2/bowtie2-build-s
sc3dg/bowtie2/bowtie2-build-s-debug
sc3dg/bowtie2/bowtie2-inspect
sc3dg/bowtie2/bowtie2-inspect-l
sc3dg/bowtie2/bowtie2-inspect-l-debug
sc3dg/bowtie2/bowtie2-inspect-s
sc3dg/bowtie2/bowtie2-inspect-s-debug
sc3dg/bowtie2/bowtie2_custombulid.py
sc3dg/bowtie2/bowtie2_wrapper.py
sc3dg/bowtie2/wrapper.py
sc3dg/bwa/COPYING
sc3dg/bwa/ChangeLog
sc3dg/bwa/Makefile
sc3dg/bwa/NEWS.md
sc3dg/bwa/QSufSort.c
sc3dg/bwa/QSufSort.h
sc3dg/bwa/QSufSort.o
sc3dg/bwa/README-alt.md
sc3dg/bwa/README.md
sc3dg/bwa/bamlite.c
sc3dg/bwa/bamlite.h
sc3dg/bwa/bamlite.o
sc3dg/bwa/bntseq.c
sc3dg/bwa/bntseq.h
sc3dg/bwa/bntseq.o
sc3dg/bwa/bwa
sc3dg/bwa/bwa.1
sc3dg-0.0.65.dist-info/METADATA
sc3dg-0.0.65.dist-info/WHEEL
sc3dg-0.0.65.dist-info/entry_points.txt
sc3dg-0.0.65.dist-info/top_level.txt
sc3dg-0.0.65.dist-info/RECORD
